pyc/__init__.py
pyc/git_test.py
pyc/pyc_model.py
pyc_regressor-0.0.2.dist-info/LICENSE
pyc_regressor-0.0.2.dist-info/METADATA
pyc_regressor-0.0.2.dist-info/WHEEL
pyc_regressor-0.0.2.dist-info/top_level.txt
pyc_regressor-0.0.2.dist-info/RECORD
